dart_fss/__init__.py
dart_fss/_version.py
dart_fss/api/__init__.py
dart_fss/api/helper.py
dart_fss/api/filings/__init__.py
dart_fss/api/filings/company.py
dart_fss/api/filings/corp_code.py
dart_fss/api/filings/document.py
dart_fss/api/filings/search_filings.py
dart_fss/api/finance/__init__.py
dart_fss/api/finance/fnltt_multi_acnt.py
dart_fss/api/finance/fnltt_singl_acnt.py
dart_fss/api/finance/fnltt_singl_acnt_all.py
dart_fss/api/finance/xbrl.py
dart_fss/api/finance/xbrl_taxonomy.py
dart_fss/api/info/__init__.py
dart_fss/api/info/accnut_adtor_nm_nd_adt_opinion.py
dart_fss/api/info/accnut_adtor_non_adt_servc_cncls_sttus.py
dart_fss/api/info/adt_servc_cncls_sttus.py
dart_fss/api/info/alot_matter.py
dart_fss/api/info/cndl_capl_scrits_nrdmp_blce.py
dart_fss/api/info/cprnd_nrdmp_blce.py
dart_fss/api/info/det_scrits_isu_acmslt.py
dart_fss/api/info/drctr_adt_all_mendng_sttus_gmtsck_confm_amount.py
dart_fss/api/info/drctr_adt_all_mendng_sttus_mendng_pymntamt_ty_cl.py
dart_fss/api/info/emp_sttus.py
dart_fss/api/info/entrprs_bil_scrits_nrdmp_blce.py
dart_fss/api/info/exctv_sttus.py
dart_fss/api/info/hmv_audit_all_sttus.py
dart_fss/api/info/hmv_audit_indvdl_by_sttus.py
dart_fss/api/info/hyslr_chg_sttus.py
dart_fss/api/info/hyslr_sttus.py
dart_fss/api/info/indvdl_by_pay.py
dart_fss/api/info/irds_sttus.py
dart_fss/api/info/mrhl_sttus.py
dart_fss/api/info/new_capl_scrits_nrdmp_blce.py
dart_fss/api/info/otr_cpr_invstmnt_sttus.py
dart_fss/api/info/outcmpny_drctr_nd_change_sttus.py
dart_fss/api/info/prvsrp_cptal_use_dtls.py
dart_fss/api/info/pssrp_cptal_use_dtls.py
dart_fss/api/info/srtpd_psndbt_nrdmp_blce.py
dart_fss/api/info/stock_totqy_sttus.py
dart_fss/api/info/tesstk_acqs_dsps_sttus.py
dart_fss/api/info/unrst_exctv_mendng_sttus.py
dart_fss/api/issue/__init__.py
dart_fss/api/issue/ast_inhtrf_etc_ptbk_opt.py
dart_fss/api/issue/bdwt_is_decsn.py
dart_fss/api/issue/bnk_mngt_pcbg.py
dart_fss/api/issue/bnk_mngt_pcsp.py
dart_fss/api/issue/bsn_inh_decsn.py
dart_fss/api/issue/bsn_sp.py
dart_fss-0.4.14.dist-info/METADATA
dart_fss-0.4.14.dist-info/WHEEL
dart_fss-0.4.14.dist-info/top_level.txt
dart_fss-0.4.14.dist-info/RECORD
