Metadata-Version: 2.4
Name: dart-fss
Version: 0.4.14
Summary: Web-scraping https://dart.fss.or.kr
Author-email: Sungwoo Jo <nonswing.z@gmail.com>
Maintainer-email: Sungwoo Jo <nonswing.z@gmail.com>
License: MIT
Project-URL: homepage, https://github.com/josw123/dart-fss
Project-URL: documentation, https://dart-fss.readthedocs.io/
Project-URL: repository, https://github.com/josw123/dart-fss.git
Keywords: fss,dart-fss,scrapping,financial_statement
Classifier: Programming Language :: Python :: 3.9
Classifier: Programming Language :: Python :: 3.10
Classifier: Programming Language :: Python :: 3.11
Classifier: Programming Language :: Python :: 3.12
Classifier: Programming Language :: Python :: 3.13
Classifier: Programming Language :: Python :: 3 :: Only
Requires-Python: >=3.7
Requires-Dist: xmltodict
Requires-Dist: requests
Requires-Dist: arelle-release
Requires-Dist: numpy
Requires-Dist: pandas
Requires-Dist: tqdm
Requires-Dist: yaspin
Requires-Dist: fake-useragent>=1.5
Requires-Dist: beautifulsoup4
Requires-Dist: appdirs
Requires-Dist: lxml
Provides-Extra: jupyter
Requires-Dist: jupyterlab; extra == "jupyter"
Requires-Dist: ipywidgets; extra == "jupyter"
